undetected/__init__.py
undetected/cdp.py
undetected/devtool.py
undetected/dprocess.py
undetected/options.py
undetected/patcher.py
undetected/reactor.py
undetected/utils/__init__.py
undetected/utils/info.py
undetected/webelement.py
undetected-0.0.11.dist-info/METADATA
undetected-0.0.11.dist-info/WHEEL
undetected-0.0.11.dist-info/licenses/LICENSE
undetected-0.0.11.dist-info/RECORD
